miscSupports/Errors.py
miscSupports/__init__.py
miscSupports/alter_array.py
miscSupports/alter_string.py
miscSupports/byte_supports.py
miscSupports/dates_and_time.py
miscSupports/file_support.py
miscSupports/misc.py
miscSupports/shapely_support.py
miscSupports-0.10.9.dist-info/LICENSE
miscSupports-0.10.9.dist-info/METADATA
miscSupports-0.10.9.dist-info/WHEEL
miscSupports-0.10.9.dist-info/top_level.txt
miscSupports-0.10.9.dist-info/RECORD
