Metadata-Version: 2.1
Name: miscSupports
Version: 0.10.9
Summary: Supporting common methods for multiple packages and repositories I have written
Home-page: UNKNOWN
Author: Samuel Baker
Author-email: samuelbaker.researcher@gmail.com
Maintainer: Samuel Baker
Maintainer-email: samuelbaker.researcher@gmail.com
License: MIT
Download-URL: https://github.com/sbaker-dev/miscSupports
Platform: UNKNOWN
Classifier: Programming Language :: Python :: 3.7
Classifier: Programming Language :: Python :: 3.8
Classifier: License :: OSI Approved :: MIT License
Requires-Python: >=3.6
Requires-Dist: numpy
Requires-Dist: PyYAML
Requires-Dist: csvObject
